text2emotion/__init__.py
text2emotion-0.0.5.dist-info/METADATA
text2emotion-0.0.5.dist-info/RECORD
text2emotion-0.0.5.dist-info/WHEEL
text2emotion-0.0.5.dist-info/top_level.txt
