Metadata-Version: 2.1
Name: text2emotion
Version: 0.0.5
Summary: Detecting emotions behind the text, text2emotion package will help you to understand the emotions in textual meassages.
Home-page: https://github.com/aman2656/text2emotion-library
Author: text2emotion Team
Author-email: Text2Emotion@gmail.com
License: MIT
Platform: UNKNOWN
Classifier: License :: OSI Approved :: MIT License
Classifier: Programming Language :: Python :: 3
Classifier: Programming Language :: Python :: 3.1
Classifier: Programming Language :: Python :: 3.2
Classifier: Programming Language :: Python :: 3.3
Classifier: Programming Language :: Python :: 3.4
Classifier: Programming Language :: Python :: 3.5
Classifier: Programming Language :: Python :: 3.6
Classifier: Programming Language :: Python :: 3.7
Classifier: Programming Language :: Python :: 3.8
